[
  {
    "exchange": "Binance",
    "tipo": "BUY",
    "cripto": "USDT",
    "fiat": "COP",
    "precio": 4130.0,
    "min": 5000000,
    "max": 40000000,
    "nickname": "Colombia_petro",
    "metodos_pago": [
      "Ualá Colombia",
      "Nequi"
    ],
    "operable": true,
    "comision_aprox": 33.04,
    "brecha": 0.0,
    "prioridad": 1,
    "link": "https://p2p.binance.com/en/advertiserDetail?advertiserNo=saf9ff7cb38fc36a293147c10519b7eee",
    "reputacion": "96.50%"
  },
  {
    "exchange": "Binance",
    "tipo": "BUY",
    "cripto": "USDT",
    "fiat": "COP",
    "precio": 4114.63,
    "min": 4000000,
    "max": 84000000,
    "nickname": "SIDDHI_SAS",
    "metodos_pago": [
      "Bancolombia S.A",
      "Davivienda S.A",
      "Nequi",
      "Daviplata"
    ],
    "operable": true,
    "comision_aprox": 32.92,
    "brecha": 0.0,
    "prioridad": 1,
    "link": "https://p2p.binance.com/en/advertiserDetail?advertiserNo=s74acb86dde613b46b0fac9398a9f01be",
    "reputacion": "100.00%"
  },
  {
    "exchange": "Binance",
    "tipo": "BUY",
    "cripto": "USDT",
    "fiat": "COP",
    "precio": 4114.62,
    "min": 3000000,
    "max": 84000000,
    "nickname": "DP_CAPITAL_SAS",
    "metodos_pago": [
      "Nequi",
      "Bancolombia S.A",
      "Davivienda S.A"
    ],
    "operable": true,
    "comision_aprox": 32.92,
    "brecha": 0.0,
    "prioridad": 1,
    "link": "https://p2p.binance.com/en/advertiserDetail?advertiserNo=s0ad56fcbb42f3cc6abebd7de539e01ba",
    "reputacion": "99.90%"
  },
  {
    "exchange": "Binance",
    "tipo": "BUY",
    "cripto": "USDT",
    "fiat": "COP",
    "precio": 4114.35,
    "min": 3000000,
    "max": 15000000,
    "nickname": "CryptoCoin3x",
    "metodos_pago": [
      "Daviplata",
      "Nequi",
      "Bancolombia S.A"
    ],
    "operable": true,
    "comision_aprox": 32.91,
    "brecha": 0.0,
    "prioridad": 1,
    "link": "https://p2p.binance.com/en/advertiserDetail?advertiserNo=s75574a987c10357bb579219eab8fd3e3",
    "reputacion": "98.70%"
  },
  {
    "exchange": "Binance",
    "tipo": "BUY",
    "cripto": "USDT",
    "fiat": "COP",
    "precio": 4114.01,
    "min": 300000,
    "max": 350000,
    "nickname": "AngelxG",
    "metodos_pago": [
      "Bancolombia S.A",
      "Nequi"
    ],
    "operable": true,
    "comision_aprox": 32.91,
    "brecha": 0.0,
    "prioridad": 1,
    "link": "https://p2p.binance.com/en/advertiserDetail?advertiserNo=sf8b325ec9f2e337db8618b331f94e7b5",
    "reputacion": "98.80%"
  },
  {
    "exchange": "Binance",
    "tipo": "BUY",
    "cripto": "USDT",
    "fiat": "COP",
    "precio": 4108.01,
    "min": 50000,
    "max": 870000,
    "nickname": "ChangeYurle",
    "metodos_pago": [
      "Nequi"
    ],
    "operable": true,
    "comision_aprox": 32.86,
    "brecha": 0.0,
    "prioridad": 1,
    "link": "https://p2p.binance.com/en/advertiserDetail?advertiserNo=sdffa6c378a8e34c09745ba1eb0235450",
    "reputacion": "98.50%"
  },
  {
    "exchange": "Binance",
    "tipo": "BUY",
    "cripto": "USDT",
    "fiat": "COP",
    "precio": 4108.0,
    "min": 200000,
    "max": 1100000,
    "nickname": "CritoCR",
    "metodos_pago": [
      "Bancolombia S.A",
      "Nequi"
    ],
    "operable": true,
    "comision_aprox": 32.86,
    "brecha": 0.0,
    "prioridad": 1,
    "link": "https://p2p.binance.com/en/advertiserDetail?advertiserNo=sacc771ce8b553f9c950cf016bceee9da",
    "reputacion": "96.20%"
  },
  {
    "exchange": "Binance",
    "tipo": "BUY",
    "cripto": "USDT",
    "fiat": "COP",
    "precio": 4106.01,
    "min": 2500000,
    "max": 40000000,
    "nickname": "CryptoGiros",
    "metodos_pago": [
      "Nequi"
    ],
    "operable": true,
    "comision_aprox": 32.85,
    "brecha": 0.0,
    "prioridad": 1,
    "link": "https://p2p.binance.com/en/advertiserDetail?advertiserNo=s5b9d508a54e03d28a4e8e8a7c269903e",
    "reputacion": "97.70%"
  },
  {
    "exchange": "Binance",
    "tipo": "BUY",
    "cripto": "USDT",
    "fiat": "COP",
    "precio": 4106.0,
    "min": 2000000,
    "max": 84000000,
    "nickname": "Web3_Strategist",
    "metodos_pago": [
      "Nequi",
      "Bancolombia S.A",
      "Davivienda S.A"
    ],
    "operable": true,
    "comision_aprox": 32.85,
    "brecha": 0.0,
    "prioridad": 1,
    "link": "https://p2p.binance.com/en/advertiserDetail?advertiserNo=s12d98f21ec3c3cd49c46ee431916be59",
    "reputacion": "100.00%"
  },
  {
    "exchange": "Binance",
    "tipo": "BUY",
    "cripto": "USDT",
    "fiat": "COP",
    "precio": 4105.0,
    "min": 45000,
    "max": 1000000,
    "nickname": "kskalfonsogiros",
    "metodos_pago": [
      "Nequi"
    ],
    "operable": true,
    "comision_aprox": 32.84,
    "brecha": 0.0,
    "prioridad": 1,
    "link": "https://p2p.binance.com/en/advertiserDetail?advertiserNo=sf96e8482fa3a32da89a0d42d066fd83f",
    "reputacion": "93.30%"
  },
  {
    "exchange": "Binance",
    "tipo": "BUY",
    "cripto": "USDT",
    "fiat": "COP",
    "precio": 4103.2,
    "min": 250000,
    "max": 7800000,
    "nickname": "dress10",
    "metodos_pago": [
      "Davivienda S.A",
      "Nequi",
      "Daviplata"
    ],
    "operable": true,
    "comision_aprox": 32.83,
    "brecha": 0.0,
    "prioridad": 1,
    "link": "https://p2p.binance.com/en/advertiserDetail?advertiserNo=s49d03103c994387e841129c252440442",
    "reputacion": "93.90%"
  },
  {
    "exchange": "Binance",
    "tipo": "BUY",
    "cripto": "USDT",
    "fiat": "COP",
    "precio": 4100.0,
    "min": 33600,
    "max": 400000,
    "nickname": "ac130nfigt",
    "metodos_pago": [
      "Bancolombia S.A",
      "Nequi",
      "Ualá Colombia",
      "Bank Transfer",
      "BBVA"
    ],
    "operable": true,
    "comision_aprox": 32.8,
    "brecha": 0.0,
    "prioridad": 1,
    "link": "https://p2p.binance.com/en/advertiserDetail?advertiserNo=sd4ff226907f638a5af22aa8bd7cf8ee5",
    "reputacion": "83.40%"
  },
  {
    "exchange": "Binance",
    "tipo": "BUY",
    "cripto": "USDT",
    "fiat": "COP",
    "precio": 4097.9,
    "min": 50000,
    "max": 9999999,
    "nickname": "mrstivencolombiastre",
    "metodos_pago": [
      "Daviplata",
      "Movii",
      "Nequi"
    ],
    "operable": true,
    "comision_aprox": 32.78,
    "brecha": 0.0,
    "prioridad": 1,
    "link": "https://p2p.binance.com/en/advertiserDetail?advertiserNo=s062dd2c2385f34dcaa3e74aec6a28021",
    "reputacion": "93.00%"
  },
  {
    "exchange": "Binance",
    "tipo": "BUY",
    "cripto": "USDT",
    "fiat": "COP",
    "precio": 4096.01,
    "min": 100000,
    "max": 804000,
    "nickname": "canbiosDD",
    "metodos_pago": [
      "Nequi",
      "Bancolombia S.A"
    ],
    "operable": true,
    "comision_aprox": 32.77,
    "brecha": 0.0,
    "prioridad": 1,
    "link": "https://p2p.binance.com/en/advertiserDetail?advertiserNo=s45406ec673f434ffaef7c1f2e06f8ef4",
    "reputacion": "94.30%"
  },
  {
    "exchange": "Binance",
    "tipo": "BUY",
    "cripto": "USDT",
    "fiat": "COP",
    "precio": 4095.02,
    "min": 34000,
    "max": 3500000,
    "nickname": "Puntopay",
    "metodos_pago": [
      "Nequi",
      "Cash Deposit to Bank",
      "Davivienda S.A",
      "Daviplata",
      "BBVA"
    ],
    "operable": true,
    "comision_aprox": 32.76,
    "brecha": 0.0,
    "prioridad": 1,
    "link": "https://p2p.binance.com/en/advertiserDetail?advertiserNo=s0660c89be67a3f1a9b27acc8c38731ae",
    "reputacion": "98.20%"
  },
  {
    "exchange": "Binance",
    "tipo": "BUY",
    "cripto": "USDT",
    "fiat": "COP",
    "precio": 4095.0,
    "min": 33600,
    "max": 2046500,
    "nickname": "safe2trust",
    "metodos_pago": [
      "Nequi",
      "Bancolombia S.A"
    ],
    "operable": true,
    "comision_aprox": 32.76,
    "brecha": 0.0,
    "prioridad": 1,
    "link": "https://p2p.binance.com/en/advertiserDetail?advertiserNo=s9adfe88d45b2320fb98fd313c4e728aa",
    "reputacion": "98.00%"
  },
  {
    "exchange": "Binance",
    "tipo": "BUY",
    "cripto": "USDT",
    "fiat": "COP",
    "precio": 4094.85,
    "min": 33600,
    "max": 13420000,
    "nickname": "SEGURIDAD-14",
    "metodos_pago": [
      "Bancolombia S.A",
      "Nequi",
      "Davivienda S.A",
      "Daviplata"
    ],
    "operable": true,
    "comision_aprox": 32.76,
    "brecha": 0.0,
    "prioridad": 1,
    "link": "https://p2p.binance.com/en/advertiserDetail?advertiserNo=s9a82ee0dc3833a38bcc799c64cbbc94a",
    "reputacion": "99.00%"
  },
  {
    "exchange": "Binance",
    "tipo": "BUY",
    "cripto": "USDT",
    "fiat": "COP",
    "precio": 4093.11,
    "min": 200000,
    "max": 671000,
    "nickname": "criptodeal",
    "metodos_pago": [
      "Nequi",
      "Bancolombia S.A"
    ],
    "operable": true,
    "comision_aprox": 32.74,
    "brecha": 0.0,
    "prioridad": 1,
    "link": "https://p2p.binance.com/en/advertiserDetail?advertiserNo=s17acb84f29333db6bdb0f3531d655309",
    "reputacion": "100.00%"
  },
  {
    "exchange": "Binance",
    "tipo": "BUY",
    "cripto": "USDT",
    "fiat": "COP",
    "precio": 4093.0,
    "min": 37000,
    "max": 1267508,
    "nickname": "kovacrypto1936",
    "metodos_pago": [
      "Daviplata",
      "Davivienda S.A",
      "Nequi",
      "Bancolombia S.A"
    ],
    "operable": true,
    "comision_aprox": 32.74,
    "brecha": 0.0,
    "prioridad": 1,
    "link": "https://p2p.binance.com/en/advertiserDetail?advertiserNo=s260a311618b63b8f9aaad4590d81a6bd",
    "reputacion": "97.70%"
  },
  {
    "exchange": "Binance",
    "tipo": "BUY",
    "cripto": "USDT",
    "fiat": "COP",
    "precio": 4092.8,
    "min": 100000,
    "max": 1022500,
    "nickname": "Alivergara7",
    "metodos_pago": [
      "Nequi"
    ],
    "operable": true,
    "comision_aprox": 32.74,
    "brecha": 0.0,
    "prioridad": 1,
    "link": "https://p2p.binance.com/en/advertiserDetail?advertiserNo=s914149327330387bb97abc7c8cff978c",
    "reputacion": "95.30%"
  },
  {
    "exchange": "Binance",
    "tipo": "SELL",
    "cripto": "USDT",
    "fiat": "COP",
    "precio": 4110.0,
    "min": 100000,
    "max": 3000000,
    "nickname": "estiven99999",
    "metodos_pago": [
      "Nequi",
      "Bancolombia S.A",
      "Bank Transfer"
    ],
    "operable": true,
    "comision_aprox": 32.88,
    "brecha": 0.0,
    "prioridad": 1,
    "link": "https://p2p.binance.com/en/advertiserDetail?advertiserNo=s5c1d4487444534399065c6f0151062cd",
    "reputacion": "100.00%"
  },
  {
    "exchange": "Binance",
    "tipo": "SELL",
    "cripto": "USDT",
    "fiat": "COP",
    "precio": 4119.99,
    "min": 2045000,
    "max": 10000000,
    "nickname": "DERPS",
    "metodos_pago": [
      "Bancolombia S.A",
      "Nequi"
    ],
    "operable": true,
    "comision_aprox": 32.96,
    "brecha": 0.0,
    "prioridad": 1,
    "link": "https://p2p.binance.com/en/advertiserDetail?advertiserNo=scd4b4d0c48133ab987162200dee92892",
    "reputacion": "98.80%"
  },
  {
    "exchange": "Binance",
    "tipo": "SELL",
    "cripto": "USDT",
    "fiat": "COP",
    "precio": 4120.0,
    "min": 700000,
    "max": 3000000,
    "nickname": "CACERES",
    "metodos_pago": [
      "Nequi",
      "Bancolombia S.A"
    ],
    "operable": true,
    "comision_aprox": 32.96,
    "brecha": 0.0,
    "prioridad": 1,
    "link": "https://p2p.binance.com/en/advertiserDetail?advertiserNo=s9b5b44dda99d3b6594b3e1ed38f624d3",
    "reputacion": "99.90%"
  },
  {
    "exchange": "Binance",
    "tipo": "SELL",
    "cripto": "USDT",
    "fiat": "COP",
    "precio": 4120.0,
    "min": 2000000,
    "max": 20000000,
    "nickname": "RJCAPITAL_TECH",
    "metodos_pago": [
      "Nequi"
    ],
    "operable": true,
    "comision_aprox": 32.96,
    "brecha": 0.0,
    "prioridad": 1,
    "link": "https://p2p.binance.com/en/advertiserDetail?advertiserNo=s976a8d92f8cc3398ade052a1be649786",
    "reputacion": "96.80%"
  },
  {
    "exchange": "Binance",
    "tipo": "SELL",
    "cripto": "USDT",
    "fiat": "COP",
    "precio": 4120.0,
    "min": 100000,
    "max": 10000000,
    "nickname": "Coin_futurejdm",
    "metodos_pago": [
      "Bancolombia S.A",
      "Nequi"
    ],
    "operable": true,
    "comision_aprox": 32.96,
    "brecha": 0.0,
    "prioridad": 1,
    "link": "https://p2p.binance.com/en/advertiserDetail?advertiserNo=s762a5fe895363121ad79384e456398ef",
    "reputacion": "98.60%"
  },
  {
    "exchange": "Binance",
    "tipo": "SELL",
    "cripto": "USDT",
    "fiat": "COP",
    "precio": 4120.84,
    "min": 1000000,
    "max": 3000000,
    "nickname": "Be_Cripto",
    "metodos_pago": [
      "Bancolombia S.A",
      "Nequi",
      "Daviplata",
      "Davivienda S.A"
    ],
    "operable": true,
    "comision_aprox": 32.97,
    "brecha": 0.0,
    "prioridad": 1,
    "link": "https://p2p.binance.com/en/advertiserDetail?advertiserNo=s29e9dd0c5cfa348a950d0d4457b8a3da",
    "reputacion": "99.60%"
  },
  {
    "exchange": "Binance",
    "tipo": "SELL",
    "cripto": "USDT",
    "fiat": "COP",
    "precio": 4123.4,
    "min": 35000,
    "max": 100000,
    "nickname": "Abogato",
    "metodos_pago": [
      "Nequi",
      "Banco de Bogota",
      "Daviplata",
      "Banco Itau Colombia"
    ],
    "operable": true,
    "comision_aprox": 32.99,
    "brecha": 0.0,
    "prioridad": 1,
    "link": "https://p2p.binance.com/en/advertiserDetail?advertiserNo=s40438a670e553288bcbb12635ad37054",
    "reputacion": "92.40%"
  },
  {
    "exchange": "Binance",
    "tipo": "SELL",
    "cripto": "USDT",
    "fiat": "COP",
    "precio": 4123.48,
    "min": 300000,
    "max": 13300000,
    "nickname": "Rapi-cripto-online",
    "metodos_pago": [
      "Davivienda S.A",
      "Daviplata",
      "Nequi",
      "Bancolombia S.A"
    ],
    "operable": true,
    "comision_aprox": 32.99,
    "brecha": 0.0,
    "prioridad": 1,
    "link": "https://p2p.binance.com/en/advertiserDetail?advertiserNo=s4a75bafe61c5387a849f74345a82b250",
    "reputacion": "100.00%"
  },
  {
    "exchange": "Binance",
    "tipo": "SELL",
    "cripto": "USDT",
    "fiat": "COP",
    "precio": 4123.75,
    "min": 700000,
    "max": 3000000,
    "nickname": "blackswan_co",
    "metodos_pago": [
      "Bancolombia S.A",
      "Nequi"
    ],
    "operable": true,
    "comision_aprox": 32.99,
    "brecha": 0.0,
    "prioridad": 1,
    "link": "https://p2p.binance.com/en/advertiserDetail?advertiserNo=s4623a8bd48d136879b9ace7c22f5bcc0",
    "reputacion": "99.70%"
  },
  {
    "exchange": "Binance",
    "tipo": "SELL",
    "cripto": "USDT",
    "fiat": "COP",
    "precio": 4123.8,
    "min": 700000,
    "max": 3000000,
    "nickname": "EL CACIQUE",
    "metodos_pago": [
      "Nequi",
      "Bancolombia S.A"
    ],
    "operable": true,
    "comision_aprox": 32.99,
    "brecha": 0.0,
    "prioridad": 1,
    "link": "https://p2p.binance.com/en/advertiserDetail?advertiserNo=s36946cba1360324bbe7b644c6686e9c7",
    "reputacion": "100.00%"
  },
  {
    "exchange": "Binance",
    "tipo": "SELL",
    "cripto": "USDT",
    "fiat": "COP",
    "precio": 4123.98,
    "min": 500000,
    "max": 8000000,
    "nickname": "TUTRADER",
    "metodos_pago": [
      "Bancolombia S.A",
      "Nequi",
      "Davivienda S.A",
      "Daviplata"
    ],
    "operable": true,
    "comision_aprox": 32.99,
    "brecha": 0.0,
    "prioridad": 1,
    "link": "https://p2p.binance.com/en/advertiserDetail?advertiserNo=s9fcd5242c92235248e7e525d7113d673",
    "reputacion": "99.80%"
  },
  {
    "exchange": "Binance",
    "tipo": "SELL",
    "cripto": "USDT",
    "fiat": "COP",
    "precio": 4124.0,
    "min": 45000,
    "max": 480000,
    "nickname": "DIVINI-LIBERTY",
    "metodos_pago": [
      "Banco de Bogota",
      "Nequi",
      "Daviplata"
    ],
    "operable": true,
    "comision_aprox": 32.99,
    "brecha": 0.0,
    "prioridad": 1,
    "link": "https://p2p.binance.com/en/advertiserDetail?advertiserNo=s7f0739607a7c3e41ab5da1aae84629c8",
    "reputacion": "100.00%"
  },
  {
    "exchange": "Binance",
    "tipo": "SELL",
    "cripto": "USDT",
    "fiat": "COP",
    "precio": 4124.99,
    "min": 100000,
    "max": 2000000,
    "nickname": "Cambiosbraycar",
    "metodos_pago": [
      "Nequi",
      "Davivienda S.A",
      "Daviplata",
      "Bancolombia S.A"
    ],
    "operable": true,
    "comision_aprox": 33.0,
    "brecha": 0.0,
    "prioridad": 1,
    "link": "https://p2p.binance.com/en/advertiserDetail?advertiserNo=s486fb9acca8932f4bacdea0f5f5fdd69",
    "reputacion": "99.60%"
  },
  {
    "exchange": "Binance",
    "tipo": "SELL",
    "cripto": "USDT",
    "fiat": "COP",
    "precio": 4125.0,
    "min": 900000,
    "max": 20000000,
    "nickname": "Nicolás Medina",
    "metodos_pago": [
      "Nequi",
      "Daviplata"
    ],
    "operable": true,
    "comision_aprox": 33.0,
    "brecha": 0.0,
    "prioridad": 1,
    "link": "https://p2p.binance.com/en/advertiserDetail?advertiserNo=s331e6ebfd7e33a3ca573217527abd389",
    "reputacion": "99.90%"
  },
  {
    "exchange": "Binance",
    "tipo": "SELL",
    "cripto": "USDT",
    "fiat": "COP",
    "precio": 4125.0,
    "min": 2000000,
    "max": 24750000,
    "nickname": "rosa1707",
    "metodos_pago": [
      "Bancolombia S.A",
      "Nequi"
    ],
    "operable": true,
    "comision_aprox": 33.0,
    "brecha": 0.0,
    "prioridad": 1,
    "link": "https://p2p.binance.com/en/advertiserDetail?advertiserNo=s6efe8bf10f77357099d4220df14184d3",
    "reputacion": "100.00%"
  },
  {
    "exchange": "Binance",
    "tipo": "SELL",
    "cripto": "USDT",
    "fiat": "COP",
    "precio": 4126.0,
    "min": 800000,
    "max": 66000000,
    "nickname": "CONTINENTAL_CO",
    "metodos_pago": [
      "Davivienda S.A",
      "BBVA",
      "Nequi"
    ],
    "operable": true,
    "comision_aprox": 33.01,
    "brecha": 0.0,
    "prioridad": 1,
    "link": "https://p2p.binance.com/en/advertiserDetail?advertiserNo=s489242e319be361687148dcded3129c1",
    "reputacion": "99.70%"
  },
  {
    "exchange": "Binance",
    "tipo": "SELL",
    "cripto": "USDT",
    "fiat": "COP",
    "precio": 4126.78,
    "min": 200000,
    "max": 4000000,
    "nickname": "Laura_Crypto-BTC",
    "metodos_pago": [
      "Nequi",
      "Bancolombia S.A"
    ],
    "operable": true,
    "comision_aprox": 33.01,
    "brecha": 0.0,
    "prioridad": 1,
    "link": "https://p2p.binance.com/en/advertiserDetail?advertiserNo=sbe3f278ad0483083bce1f3e3875a14dc",
    "reputacion": "100.00%"
  },
  {
    "exchange": "Binance",
    "tipo": "SELL",
    "cripto": "USDT",
    "fiat": "COP",
    "precio": 4126.8,
    "min": 150000,
    "max": 30000000,
    "nickname": "DANIEL_CRIPTOP2P",
    "metodos_pago": [
      "Nequi"
    ],
    "operable": true,
    "comision_aprox": 33.01,
    "brecha": 0.0,
    "prioridad": 1,
    "link": "https://p2p.binance.com/en/advertiserDetail?advertiserNo=s77e0353ae88b3e00a34e32ef6c56d93d",
    "reputacion": "99.60%"
  },
  {
    "exchange": "Binance",
    "tipo": "SELL",
    "cripto": "USDT",
    "fiat": "COP",
    "precio": 4126.9,
    "min": 150000,
    "max": 13000000,
    "nickname": "InversionSanba",
    "metodos_pago": [
      "Nequi",
      "Bancolombia S.A"
    ],
    "operable": true,
    "comision_aprox": 33.02,
    "brecha": 0.0,
    "prioridad": 1,
    "link": "https://p2p.binance.com/en/advertiserDetail?advertiserNo=sd37d734f8ee534e6b5e07295c4725e48",
    "reputacion": "100.00%"
  },
  {
    "exchange": "Binance",
    "tipo": "SELL",
    "cripto": "USDT",
    "fiat": "COP",
    "precio": 4126.9,
    "min": 400000,
    "max": 10000000,
    "nickname": "DON_TITO",
    "metodos_pago": [
      "Davivienda S.A",
      "Nequi",
      "BBVA"
    ],
    "operable": true,
    "comision_aprox": 33.02,
    "brecha": 0.0,
    "prioridad": 1,
    "link": "https://p2p.binance.com/en/advertiserDetail?advertiserNo=s78b02e0abe053dc786446aa2b5dd5944",
    "reputacion": "99.10%"
  }
]